flake8_simple_var/__init__.py
flake8_simple_var/entry.py
flake8_simple_var/py.typed
flake8_simple_var-0.1.0.dist-info/LICENSE
flake8_simple_var-0.1.0.dist-info/METADATA
flake8_simple_var-0.1.0.dist-info/WHEEL
flake8_simple_var-0.1.0.dist-info/entry_points.txt
flake8_simple_var-0.1.0.dist-info/RECORD
