Metadata-Version: 2.3
Name: flake8-simple-var
Version: 0.1.0
Summary: flake8 plugin for checking variable names contain only one word
License: MIT
Keywords: flake8,linting,variable-names,code-quality,python
Author: Almaz Ilaletdinov
Author-email: a.ilaletdinov@yandex.ru
Requires-Python: >=3.9,<4.0
Classifier: Development Status :: 3 - Alpha
Classifier: Intended Audience :: Developers
Classifier: License :: OSI Approved :: MIT License
Classifier: Operating System :: OS Independent
Classifier: Programming Language :: Python :: 3
Classifier: Programming Language :: Python :: 3.9
Classifier: Programming Language :: Python :: 3.10
Classifier: Programming Language :: Python :: 3.11
Classifier: Programming Language :: Python :: 3.12
Classifier: Programming Language :: Python :: 3.13
Classifier: Topic :: Software Development :: Libraries :: Python Modules
Requires-Dist: flake8 (>=7.1,<8.0)
Project-URL: Repository, https://github.com/blablatdinov/flake8-simple-var
